olira/__init__.py
olira-0.1.0.dist-info/licenses/LICENSE
olira-0.1.0.dist-info/METADATA
olira-0.1.0.dist-info/WHEEL
olira-0.1.0.dist-info/top_level.txt
olira-0.1.0.dist-info/RECORD
