Metadata-Version: 2.4
Name: olira
Version: 0.1.0
Summary: Olira AI - Health and wellness technology platform
Author-email: Olira AI <dev@olira.ai>
License: MIT
Project-URL: Homepage, https://olira.ai
Project-URL: Documentation, https://github.com/raia-health/olira-common-models
Project-URL: Source, https://github.com/raia-health/olira-common-models
Keywords: olira,health,wellness,ai
Classifier: Development Status :: 2 - Pre-Alpha
Classifier: Intended Audience :: Developers
Classifier: License :: OSI Approved :: MIT License
Classifier: Programming Language :: Python :: 3
Classifier: Programming Language :: Python :: 3.11
Classifier: Programming Language :: Python :: 3.12
Classifier: Operating System :: OS Independent
Classifier: Topic :: Software Development :: Libraries :: Python Modules
Requires-Python: >=3.11
License-File: LICENSE
Dynamic: license-file
